CHANGELOG
CODE_OF_CONDUCT.md
CONTRIBUTING.rst
CONTRIBUTORS
LICENSE
MANIFEST.in
README.rst
VERSION
sample.txt
setup.py
PlayerPiano.egg-info/PKG-INFO
PlayerPiano.egg-info/SOURCES.txt
PlayerPiano.egg-info/dependency_links.txt
PlayerPiano.egg-info/entry_points.txt
PlayerPiano.egg-info/requires.txt
PlayerPiano.egg-info/top_level.txt
playerpiano/__init__.py
playerpiano/fifo_target.py
playerpiano/piano.py
playerpiano/recorder.py
playerpiano/terminal_highlighter.py
playerpiano/terminal_target.py