Metadata-Version: 1.1
Name: PlayerPiano
Version: 0.3.0
Summary: Amaze your friends by running Python doctests in a fake interactive shell
Home-page: https://github.com/wearpants/playerpiano
Author: Peter Fein
Author-email: pete@wearpants.org
License: BSD
Platform: UNKNOWN
Classifier: Development Status :: 5 - Production/Stable
Classifier: Environment :: Console
Classifier: Intended Audience :: Developers
Classifier: Operating System :: POSIX
Classifier: Topic :: Education :: Computer Aided Instruction (CAI)
Classifier: Topic :: System :: Shells
